h5yaml/conf_from_yaml.py
h5yaml/yaml_h5.py
h5yaml/yaml_nc.py
h5yaml/Data/h5_testing.yaml
h5yaml/Data/nc_testing.yaml
h5yaml/lib/chunksizes.py
h5yaml-0.1.0.dist-info/METADATA
h5yaml-0.1.0.dist-info/WHEEL
h5yaml-0.1.0.dist-info/licenses/LICENSE
h5yaml-0.1.0.dist-info/RECORD
