Metadata-Version: 2.4
Name: h5yaml
Version: 0.1.0
Summary: Use YAML configuration file to generate HDF5/netCDF4 formated files.
Project-URL: Homepage, https://github.com/rmvanhees/h5_yaml
Project-URL: Source, https://github.com/rmvanhees/h5_yaml
Project-URL: Issues, https://github.com/rmvanhees/h5_yaml/issues
Author-email: Richard van Hees <r.m.van.hees@sron.nl>
License-Expression: BSD-3-Clause
License-File: LICENSE
Keywords: HDF5,YAML,netCDF4
Classifier: Development Status :: 5 - Production/Stable
Classifier: Intended Audience :: Developers
Classifier: Intended Audience :: Science/Research
Classifier: Operating System :: OS Independent
Classifier: Programming Language :: Python :: 3 :: Only
Classifier: Programming Language :: Python :: 3.10
Classifier: Programming Language :: Python :: 3.11
Classifier: Programming Language :: Python :: 3.12
Classifier: Programming Language :: Python :: 3.13
Classifier: Programming Language :: Python :: 3.14
Classifier: Topic :: Scientific/Engineering :: Atmospheric Science
Requires-Python: >=3.10
Requires-Dist: h5py>=3.13
Requires-Dist: netcdf4>=1.7
Requires-Dist: numpy>=2.2
Requires-Dist: pyyaml>=6.0
